soldocs/__init__.py
soldocs/main.py
soldocs-0.1.1.dist-info/METADATA
soldocs-0.1.1.dist-info/RECORD
soldocs-0.1.1.dist-info/WHEEL
soldocs-0.1.1.dist-info/entry_points.txt
soldocs-0.1.1.dist-info/top_level.txt
