Metadata-Version: 2.1
Name: soldocs
Version: 0.1.1
Summary: UNKNOWN
Home-page: https://github.com/kuip/soldocs
Author: Loredana Cirstea
Author-email: loredana.cirstea@gmail.com
License: MIT
Keywords: populus solidity natspec documentation
Platform: UNKNOWN
Classifier: Development Status :: 3 - Alpha
Classifier: Intended Audience :: Developers
Classifier: License :: OSI Approved :: MIT License
Classifier: Programming Language :: Python :: 3
Classifier: Programming Language :: Python :: 3.4
Requires-Dist: click
